contentgen/__init__.py
contentgen/_version.py
contentgen/handlers.py
contentgen/labextension/package.json
contentgen/labextension/static/401.5ba5b993b324c0ca5069.js
contentgen/labextension/static/728.5ec04a4b3d5f33c3c94d.js
contentgen/labextension/static/remoteEntry.b919670f368fb36231a0.js
contentgen/labextension/static/style.js
contentgen/labextension/static/third-party-licenses.json
contentgen/tests/__init__.py
contentgen/tests/test_handlers.py
contentgen-0.1.6.data/data/etc/jupyter/jupyter_server_config.d/contentgen.json
contentgen-0.1.6.data/data/share/jupyter/labextensions/contentgen/package.json
contentgen-0.1.6.data/data/share/jupyter/labextensions/contentgen/static/401.5ba5b993b324c0ca5069.js
contentgen-0.1.6.data/data/share/jupyter/labextensions/contentgen/static/728.5ec04a4b3d5f33c3c94d.js
contentgen-0.1.6.data/data/share/jupyter/labextensions/contentgen/static/remoteEntry.b919670f368fb36231a0.js
contentgen-0.1.6.data/data/share/jupyter/labextensions/contentgen/static/style.js
contentgen-0.1.6.data/data/share/jupyter/labextensions/contentgen/static/third-party-licenses.json
contentgen-0.1.6.data/data/share/jupyter/labextensions/contentgen/install.json
contentgen-0.1.6.dist-info/METADATA
contentgen-0.1.6.dist-info/WHEEL
contentgen-0.1.6.dist-info/licenses/LICENSE
contentgen-0.1.6.dist-info/RECORD
